imgdup.py
setup.py
imgdup.egg-info/PKG-INFO
imgdup.egg-info/SOURCES.txt
imgdup.egg-info/dependency_links.txt
imgdup.egg-info/requires.txt
imgdup.egg-info/top_level.txt