Metadata-Version: 1.0
Name: imgdup
Version: 1.3
Summary: Visual similarity image finder and cleaner (image deduplication tool)
Home-page: https://github.com/rif/imgdup
Author: Radu Ioan Fericean
Author-email: radu@fericean.ro
License: MIT
Keywords: deduplication duplicate images image visual finder
Platform: UNKNOWN
